[
  {
    "title": "JavaScript",
	"subheader": "COMING SOON",
    "description": ["Basics", "Advanced","QnA", "Projects","Interview Questions"],
    "buttonText": "Read Now",
    "buttonVariant": "outlined",
	"link": ""
  },
  {
    "title": "CapsQuiz",
	"subheader": "COMING SOON",
    "description": ["All Quiz QnA","Quiz Explanations","Conceptual QnA","And many More"],
    "buttonText": "Read Now",
    "buttonVariant": "outlined",
	"link": ""
  },
  {
    "title": "HTML5",
    "subheader": "COMING SOON",
    "description": ["Basics","All Tags Ex.","Project","Interview Questions"],
    "buttonText": "Read Now",
    "buttonVariant": "outlined",
	"link": ""
  },
  {
    "title": "CSS3",
	"subheader": "COMING SOON",
    "description": ["Basics","All Tags Ex.","Project","Interview Questions"],
    "buttonText": "Read Now",
    "buttonVariant": "outlined",
	"link": ""
  },
  {
    "title": "C",
	"subheader": "Most popular",
    "description": ["Basics","Advanced","Conceptual QnA","Interview QnA"],
    "buttonText": "Read Now",
    "buttonVariant": "outlined",
	"whatsapp": ""
  }
]